fedpydeseq2/__init__.py
fedpydeseq2/core/__init__.py
fedpydeseq2/core/deseq2_core/__init__.py
fedpydeseq2/core/deseq2_core/build_design_matrix/__init__.py
fedpydeseq2/core/deseq2_core/build_design_matrix/build_design_matrix.py
fedpydeseq2/core/deseq2_core/build_design_matrix/substeps.py
fedpydeseq2/core/deseq2_core/compute_cook_distance/__init__.py
fedpydeseq2/core/deseq2_core/compute_cook_distance/compute_cook_distance.py
fedpydeseq2/core/deseq2_core/compute_cook_distance/substeps.py
fedpydeseq2/core/deseq2_core/compute_size_factors/__init__.py
fedpydeseq2/core/deseq2_core/compute_size_factors/compute_size_factors.py
fedpydeseq2/core/deseq2_core/compute_size_factors/substeps.py
fedpydeseq2/core/deseq2_core/deseq2_full_pipe.py
fedpydeseq2/core/deseq2_core/deseq2_lfc_dispersions/__init__.py
fedpydeseq2/core/deseq2_core/deseq2_lfc_dispersions/compute_MAP_dispersions/__init__.py
fedpydeseq2/core/deseq2_core/deseq2_lfc_dispersions/compute_MAP_dispersions/compute_MAP_dispersions.py
fedpydeseq2/core/deseq2_core/deseq2_lfc_dispersions/compute_MAP_dispersions/substeps.py
fedpydeseq2/core/deseq2_core/deseq2_lfc_dispersions/compute_dispersion_prior/__init__.py
fedpydeseq2/core/deseq2_core/deseq2_lfc_dispersions/compute_dispersion_prior/compute_dispersion_prior.py
fedpydeseq2/core/deseq2_core/deseq2_lfc_dispersions/compute_dispersion_prior/substeps.py
fedpydeseq2/core/deseq2_core/deseq2_lfc_dispersions/compute_dispersion_prior/utils.py
fedpydeseq2/core/deseq2_core/deseq2_lfc_dispersions/compute_genewise_dispersions/__init__.py
fedpydeseq2/core/deseq2_core/deseq2_lfc_dispersions/compute_genewise_dispersions/compute_MoM_dispersions/__init__.py
fedpydeseq2/core/deseq2_core/deseq2_lfc_dispersions/compute_genewise_dispersions/compute_MoM_dispersions/compute_MoM_dispersions.py
fedpydeseq2/core/deseq2_core/deseq2_lfc_dispersions/compute_genewise_dispersions/compute_MoM_dispersions/compute_rough_dispersions.py
fedpydeseq2-0.1.1.dist-info/LICENSE
fedpydeseq2-0.1.1.dist-info/METADATA
fedpydeseq2-0.1.1.dist-info/WHEEL
fedpydeseq2-0.1.1.dist-info/RECORD
